py_nest_thermostat/__init__.py
py_nest_thermostat/auth.py
py_nest_thermostat/config.py
py_nest_thermostat/connectors/base.py
py_nest_thermostat/connectors/cockroach_db.py
py_nest_thermostat/connectors/postgres.py
py_nest_thermostat/logger.py
py_nest_thermostat/main.py
py_nest_thermostat/models.py
py_nest_thermostat/nest_api.py
py_nest_thermostat-0.0.8.dist-info/entry_points.txt
py_nest_thermostat-0.0.8.dist-info/LICENSE
py_nest_thermostat-0.0.8.dist-info/WHEEL
py_nest_thermostat-0.0.8.dist-info/METADATA
py_nest_thermostat-0.0.8.dist-info/RECORD
