Metadata-Version: 2.1
Name: py-nest-thermostat
Version: 0.0.8
Summary: A Python CLI Nest Thermostat controller and dashborading tool
Home-page: https://github.com/bastienboutonnet/py-nest-thermostat
License: MIT
Keywords: cli-app,nest,google,iot
Author: Bastien Boutonnet
Author-email: bastien.b1@gmail.com
Requires-Python: >=3.9,<4.0
Classifier: Development Status :: 3 - Alpha
Classifier: Intended Audience :: Developers
Classifier: License :: OSI Approved :: MIT License
Classifier: Programming Language :: Python :: 3
Classifier: Programming Language :: Python :: 3.10
Classifier: Programming Language :: Python :: 3.9
Classifier: Topic :: Software Development :: Build Tools
Requires-Dist: SQLAlchemy (>=1.4.27,<2.0.0)
Requires-Dist: cleo (>=0.8.1,<0.9.0)
Requires-Dist: httpx (>=0.20.0,<0.21.0)
Requires-Dist: psycopg2-binary (>=2.9.1,<3.0.0)
Requires-Dist: pyaml (>=21.10.1,<22.0.0)
Requires-Dist: pydantic (>=1.8.2,<2.0.0)
Requires-Dist: questionary (>=1.10.0,<2.0.0)
Requires-Dist: rich (>=10.13.0,<11.0.0)
Requires-Dist: sqlalchemy-cockroachdb (>=1.4.2,<2.0.0)
Project-URL: Repository, https://github.com/bastienboutonnet/py-nest-thermostat
